{
  "$schema": "https://developer.microsoft.com/json-schemas/fabric/item/report/definition/visualContainer/2.5.0/schema.json",
  "name": "fd9cac0a7e8a8d61a272",
  "position": {
    "x": 15.306122448979588,
    "y": 16.3265306122449,
    "z": 7000,
    "height": 96.938775510204081,
    "width": 174.48979591836735,
    "tabOrder": 7000
  },
  "visual": {
    "visualType": "slicer",
    "query": {
      "queryState": {
        "Values": {
          "projections": [
            {
              "field": {
                "Column": {
                  "Expression": {
                    "SourceRef": {
                      "Entity": "Calendario"
                    }
                  },
                  "Property": "Date"
                }
              },
              "queryRef": "Calendario.Date",
              "nativeQueryRef": "Date",
              "active": true
            }
          ]
        }
      },
      "sortDefinition": {
        "sort": [
          {
            "field": {
              "Column": {
                "Expression": {
                  "SourceRef": {
                    "Entity": "Calendario"
                  }
                },
                "Property": "Date"
              }
            },
            "direction": "Ascending"
          }
        ],
        "isDefaultSort": true
      }
    },
    "objects": {
      "data": [
        {
          "properties": {
            "startDate": {
              "expr": {
                "Literal": {
                  "Value": "datetime'2025-09-01T00:00:00'"
                }
              }
            },
            "endDate": {
              "expr": {
                "Literal": {
                  "Value": "datetime'2025-09-30T00:00:00'"
                }
              }
            },
            "mode": {
              "expr": {
                "Literal": {
                  "Value": "'Between'"
                }
              }
            }
          }
        }
      ],
      "dateRange": [
        {
          "properties": {
            "includeToday": {
              "expr": {
                "Literal": {
                  "Value": "true"
                }
              }
            }
          }
        }
      ],
      "general": [
        {
          "properties": {
            "filter": {
              "filter": {
                "Version": 2,
                "From": [
                  {
                    "Name": "c",
                    "Entity": "Calendario",
                    "Type": 0
                  }
                ],
                "Where": [
                  {
                    "Condition": {
                      "And": {
                        "Left": {
                          "Comparison": {
                            "ComparisonKind": 2,
                            "Left": {
                              "Column": {
                                "Expression": {
                                  "SourceRef": {
                                    "Source": "c"
                                  }
                                },
                                "Property": "Date"
                              }
                            },
                            "Right": {
                              "Literal": {
                                "Value": "datetime'2025-09-01T00:00:00'"
                              }
                            }
                          }
                        },
                        "Right": {
                          "Comparison": {
                            "ComparisonKind": 3,
                            "Left": {
                              "Column": {
                                "Expression": {
                                  "SourceRef": {
                                    "Source": "c"
                                  }
                                },
                                "Property": "Date"
                              }
                            },
                            "Right": {
                              "Literal": {
                                "Value": "datetime'2025-10-01T00:00:00'"
                              }
                            }
                          }
                        }
                      }
                    }
                  }
                ]
              }
            }
          }
        }
      ],
      "slider": [
        {
          "properties": {
            "show": {
              "expr": {
                "Literal": {
                  "Value": "false"
                }
              }
            }
          }
        }
      ]
    },
    "visualContainerObjects": {
      "background": [
        {
          "properties": {
            "transparency": {
              "expr": {
                "Literal": {
                  "Value": "0D"
                }
              }
            },
            "color": {
              "solid": {
                "color": {
                  "expr": {
                    "ThemeDataColor": {
                      "ColorId": 0,
                      "Percent": 0
                    }
                  }
                }
              }
            }
          }
        }
      ],
      "border": [
        {
          "properties": {
            "show": {
              "expr": {
                "Literal": {
                  "Value": "true"
                }
              }
            },
            "radius": {
              "expr": {
                "Literal": {
                  "Value": "12D"
                }
              }
            }
          }
        }
      ],
      "title": [
        {
          "properties": {
            "show": {
              "expr": {
                "Literal": {
                  "Value": "false"
                }
              }
            }
          }
        }
      ]
    },
    "drillFilterOtherVisuals": true
  }
}